gamdam/__init__.py
gamdam/__main__.py
gamdam/aioutil.py
gamdam/core.py
gamdam/py.typed
gamdam-0.5.0.dist-info/METADATA
gamdam-0.5.0.dist-info/WHEEL
gamdam-0.5.0.dist-info/entry_points.txt
gamdam-0.5.0.dist-info/licenses/LICENSE
gamdam-0.5.0.dist-info/RECORD
