Metadata-Version: 2.1
Name: gamdam
Version: 0.5.0
Summary: Git-Annex Mass Downloader and Metadata-er
Project-URL: Source Code, https://github.com/jwodder/gamdam
Project-URL: Bug Tracker, https://github.com/jwodder/gamdam/issues
Author-email: John Thorvald Wodder II <gamdam@varonathe.org>
License-Expression: MIT
License-File: LICENSE
Keywords: anyio,async,download,git-annex
Classifier: Development Status :: 7 - Inactive
Classifier: Environment :: Console
Classifier: Framework :: AnyIO
Classifier: Intended Audience :: End Users/Desktop
Classifier: License :: OSI Approved :: MIT License
Classifier: Programming Language :: Python :: 3
Classifier: Programming Language :: Python :: 3 :: Only
Classifier: Programming Language :: Python :: 3.8
Classifier: Programming Language :: Python :: 3.9
Classifier: Programming Language :: Python :: 3.10
Classifier: Programming Language :: Python :: 3.11
Classifier: Programming Language :: Python :: Implementation :: CPython
Classifier: Programming Language :: Python :: Implementation :: PyPy
Classifier: Topic :: Communications :: File Sharing
Classifier: Topic :: Internet
Classifier: Topic :: Internet :: File Transfer Protocol (FTP)
Classifier: Topic :: Internet :: WWW/HTTP
Classifier: Typing :: Typed
Requires-Python: >=3.8
Requires-Dist: anyio~=4.0
Requires-Dist: async-generator~=1.10; python_version < '3.10'
Requires-Dist: click-loglevel~=0.5
Requires-Dist: click>=8.0
Requires-Dist: linesep~=0.4
Requires-Dist: pydantic~=2.0
